setup.py
Bilals_pypkg.egg-info/PKG-INFO
Bilals_pypkg.egg-info/SOURCES.txt
Bilals_pypkg.egg-info/dependency_links.txt
Bilals_pypkg.egg-info/not-zip-safe
Bilals_pypkg.egg-info/top_level.txt
distributions/Binomialdistribution.py
distributions/Gaussiandistribution.py
distributions/Generaldistribution.py
distributions/__init__.py