Metadata-Version: 1.0
Name: Bilals-pypkg
Version: 0.1
Summary: Gaussian distributions
Home-page: UNKNOWN
Author: Bilal Shakeel
Author-email: bilal_786shakeel@yahoo.com
License: UNKNOWN
Platform: UNKNOWN
